flake8_test_docs.py
flake8_test_docs-1.0.8.dist-info/entry_points.txt
flake8_test_docs-1.0.8.dist-info/METADATA
flake8_test_docs-1.0.8.dist-info/LICENSE
flake8_test_docs-1.0.8.dist-info/WHEEL
flake8_test_docs-1.0.8.dist-info/RECORD
