Metadata-Version: 2.1
Name: flake8-test-docs
Version: 1.0.8
Summary: A linter that checks test docstrings for the arrange/act/assert structure
License: Apache 2.0
Author: David Andersson
Author-email: david@jdkandersson.com
Requires-Python: >=3.8.1,<4.0.0
Classifier: Environment :: Console
Classifier: Framework :: Flake8
Classifier: Intended Audience :: Developers
Classifier: License :: OSI Approved :: Apache Software License
Classifier: License :: Other/Proprietary License
Classifier: Programming Language :: Python
Classifier: Programming Language :: Python :: 3
Classifier: Programming Language :: Python :: 3.9
Classifier: Programming Language :: Python :: 3.10
Classifier: Programming Language :: Python :: 3.11
Classifier: Programming Language :: Python :: 3
Classifier: Programming Language :: Python :: 3.10
Classifier: Programming Language :: Python :: 3.11
Classifier: Programming Language :: Python :: 3.8
Classifier: Programming Language :: Python :: 3.9
Classifier: Topic :: Software Development :: Libraries :: Python Modules
Classifier: Topic :: Software Development :: Quality Assurance
Requires-Dist: flake8 (>=5)
Requires-Dist: typing_extensions (>=4,<5) ; python_version < "3.10"
